{
  "keys": {
    "oi": {
      "duration": "2s",
      "active": true,
      "owner": "sh",
      "first_use": null,
      "device_limit": 1,
      "perm": false
    },
    "lvdapaz": {
      "duration": "7d",
      "active": true,
      "owner": "d",
      "first_use": null,
      "device_limit": 1,
      "perm": false
    },
    "spark": {
      "active": true,
      "owner": "gratis",
      "first_use": 1764380848368,
      "perm": false,
      "duration": "1d"
    },
    "KEY-2SECONDS-A9ZNCYQVFO": {
      "perm": false,
      "active": true,
      "owner": "hs",
      "first_use": null,
      "device_limit": 1,
      "duration": "2s"
    },
    "testi": {
      "duration": "3s",
      "perm": false,
      "active": true,
      "first_use": null,
      "owner": "TESTE SPARK",
      "device_limit": 1
    }
  }
}